<?xml version="1.0" encoding="UTF-8"?>
<root>


<date>
    <id>3</id>
    <nume>albastrele</nume>
    <culoare>albe</culoare>
    <marime>medii</marime>
    <pret>21</pret>
     <view>view.php?id=3</view>
    <edit>edit.php?id=3</edit>
    <delete>delete.php?id=3</delete>
    <confirm>return confirm('Are you sure you want to delete this item?')</confirm>
    <back>index.php</back>
</date>
<date><id/><nume>zambile</nume><culoare>mov</culoare><marime>mari</marime><pret>10</pret><view>view.php?id=</view><edit>edit.php?id=</edit><delete>delete.php?id=</delete><confirm>return confirm("Are you sure you want to delete this item?")</confirm><back>index.php</back></date></root>
